odoo10_addon_purchase_order_line_description-10.0.1.0.0-py2.7-nspkg.pth
odoo/addons/purchase_order_line_description/README.rst
odoo/addons/purchase_order_line_description/__init__.py
odoo/addons/purchase_order_line_description/__manifest__.py
odoo/addons/purchase_order_line_description/i18n/de.po
odoo/addons/purchase_order_line_description/i18n/es.po
odoo/addons/purchase_order_line_description/i18n/es_MX.po
odoo/addons/purchase_order_line_description/i18n/fi.po
odoo/addons/purchase_order_line_description/i18n/fr.po
odoo/addons/purchase_order_line_description/i18n/it.po
odoo/addons/purchase_order_line_description/i18n/nl_NL.po
odoo/addons/purchase_order_line_description/i18n/pt_BR.po
odoo/addons/purchase_order_line_description/i18n/pt_PT.po
odoo/addons/purchase_order_line_description/i18n/ro.po
odoo/addons/purchase_order_line_description/i18n/sl.po
odoo/addons/purchase_order_line_description/models/__init__.py
odoo/addons/purchase_order_line_description/models/purchase_config_settings.py
odoo/addons/purchase_order_line_description/models/purchase_order_line.py
odoo/addons/purchase_order_line_description/security/res_groups_security.xml
odoo/addons/purchase_order_line_description/static/description/icon.png
odoo/addons/purchase_order_line_description/tests/__init__.py
odoo/addons/purchase_order_line_description/tests/test_purchase_order_line_description.py
odoo/addons/purchase_order_line_description/views/purchase_config_settings_view.xml
odoo10_addon_purchase_order_line_description-10.0.1.0.0.dist-info/DESCRIPTION.rst
odoo10_addon_purchase_order_line_description-10.0.1.0.0.dist-info/METADATA
odoo10_addon_purchase_order_line_description-10.0.1.0.0.dist-info/RECORD
odoo10_addon_purchase_order_line_description-10.0.1.0.0.dist-info/WHEEL
odoo10_addon_purchase_order_line_description-10.0.1.0.0.dist-info/metadata.json
odoo10_addon_purchase_order_line_description-10.0.1.0.0.dist-info/namespace_packages.txt
odoo10_addon_purchase_order_line_description-10.0.1.0.0.dist-info/top_level.txt
